{
  "questions": [
    {
      "id": 1,
      "question": "پایتخت ایران کجاست؟",
      "options": ["اصفهان", "تهران", "شیراز", "مشهد"],
      "answer": "تهران"
    },
    {
      "id": 2,
      "question": "بزرگترین قاره جهان کدام است؟",
      "options": ["آفریقا", "اروپا", "آسیا", "آمریکا"],
      "answer": "آسیا"
    },
    {
      "id": 3,
      "question": "کدام سیاره به سیاره سرخ معروف است؟",
      "options": ["مریخ", "زهره", "عطارد", "زمین"],
      "answer": "مریخ"
    },
    {
      "id": 4,
      "question": "نویسنده کتاب شاهنامه کیست؟",
      "options": ["فردوسی", "سعدی", "مولوی", "خیام"],
      "answer": "فردوسی"
    },
    {
      "id": 5,
      "question": "کدام حیوان بزرگترین پستاندار جهان است؟",
      "options": ["فیل", "نهنگ آبی", "اسب آبی", "کوسه"],
      "answer": "نهنگ آبی"
    },
    {
      "id": 6,
      "question": "اولین انسان روی ماه چه کسی بود؟",
      "options": ["یوری گاگارین", "نیل آرمسترانگ", "مایکل کالینز", "باز آلدرین"],
      "answer": "نیل آرمسترانگ"
    },
    {
      "id": 7,
      "question": "کدام کشور به سرزمین آفتاب تابان معروف است؟",
      "options": ["چین", "هند", "ژاپن", "کره جنوبی"],
      "answer": "ژاپن"
    },
    {
      "id": 8,
      "question": "کدام دریاچه بزرگترین دریاچه جهان است؟",
      "options": ["دریاچه خزر", "دریاچه ویکتوریا", "دریاچه سوپریور", "دریاچه بایکال"],
      "answer": "دریاچه خزر"
    },
    {
      "id": 9,
      "question": "سرعت نور تقریبا چند کیلومتر در ثانیه است؟",
      "options": ["۳۰۰ هزار", "۱۵۰ هزار", "۱۰۰ هزار", "۵۰۰ هزار"],
      "answer": "۳۰۰ هزار"
    },
    {
      "id": 10,
      "question": "کدام کشور بیشترین جمعیت جهان را دارد؟",
      "options": ["هند", "چین", "آمریکا", "اندونزی"],
      "answer": "چین"
    },
    {
      "id": 11,
      "question": "نماد شیمیایی طلا چیست؟",
      "options": ["Au", "Ag", "Fe", "Pt"],
      "answer": "Au"
    },
    {
      "id": 12,
      "question": "ارتفاع قله دماوند تقریبا چند متر است؟",
      "options": ["۴۶۰۰", "۵۶۰۰", "۵۶۷۰", "۶۱۰۰"],
      "answer": "۵۶۷۰"
    },
    {
      "id": 13,
      "question": "کشور برزیل در کدام قاره قرار دارد؟",
      "options": ["آفریقا", "آسیا", "آمریکای جنوبی", "اروپا"],
      "answer": "آمریکای جنوبی"
    },
    {
      "id": 14,
      "question": "کدام شاعر ایرانی به لسان‌الغیب معروف است؟",
      "options": ["سعدی", "حافظ", "مولوی", "خیام"],
      "answer": "حافظ"
    },
    {
      "id": 15,
      "question": "کدام حیوان سریع‌ترین موجود روی خشکی است؟",
      "options": ["اسب", "یوزپلنگ", "خرگوش", "شیر"],
      "answer": "یوزپلنگ"
    },
    {
      "id": 16,
      "question": "کدام کشور میزبان المپیک ۲۰۲۰ بود؟",
      "options": ["چین", "برزیل", "ژاپن", "انگلستان"],
      "answer": "ژاپن"
    },
    {
      "id": 17,
      "question": "بزرگترین اقیانوس جهان کدام است؟",
      "options": ["اقیانوس هند", "اقیانوس اطلس", "اقیانوس آرام", "اقیانوس منجمد شمالی"],
      "answer": "اقیانوس آرام"
    },
    {
      "id": 18,
      "question": "رئیس‌جمهور فعلی آمریکا در سال ۲۰۲۵ چه کسی است؟",
      "options": ["دونالد ترامپ", "جو بایدن", "باراک اوباما", "جورج بوش"],
      "answer": "جو بایدن"
    },
    {
      "id": 19,
      "question": "کدام سیاره بزرگترین سیاره منظومه شمسی است؟",
      "options": ["مشتری", "زحل", "اورانوس", "نپتون"],
      "answer": "مشتری"
    },
    {
      "id": 20,
      "question": "واحد پول ژاپن چیست؟",
      "options": ["ین", "دلار", "یورو", "یوان"],
      "answer": "ین"
    },
    {
      "id": 21,
      "question": "کدام کشور به خاطر برج ایفل مشهور است؟",
      "options": ["آلمان", "فرانسه", "ایتالیا", "انگلستان"],
      "answer": "فرانسه"
    },
    {
      "id": 22,
      "question": "کدام دانشمند نظریه نسبیت را ارائه داد؟",
      "options": ["نیوتن", "گالیله", "انیشتین", "کپلر"],
      "answer": "انیشتین"
    },
    {
      "id": 23,
      "question": "کدام درخت نماد صلح است؟",
      "options": ["انجیر", "زیتون", "بلوط", "نارون"],
      "answer": "زیتون"
    },
    {
      "id": 24,
      "question": "کدام کشور بیشترین جمعیت مسلمان جهان را دارد؟",
      "options": ["ایران", "اندونزی", "پاکستان", "ترکیه"],
      "answer": "اندونزی"
    },
    {
      "id": 25,
      "question": "کدام قاره به قاره سیاه معروف است؟",
      "options": ["آسیا", "آفریقا", "اروپا", "آمریکا"],
      "answer": "آفریقا"
    },
    {
      "id": 26,
      "question": "کدام حیوان به سلطان جنگل معروف است؟",
      "options": ["ببر", "شیر", "فیل", "پلنگ"],
      "answer": "شیر"
    },
    {
      "id": 27,
      "question": "کدام کشور به خاطر دیوار بزرگ مشهور است؟",
      "options": ["چین", "هند", "ژاپن", "کره جنوبی"],
      "answer": "چین"
    },
    {
      "id": 28,
      "question": "بلندترین کوه جهان کدام است؟",
      "options": ["اورست", "دماوند", "آراگاتس", "آلپ"],
      "answer": "اورست"
    },
    {
      "id": 29,
      "question": "اولین پیامبر در ادیان ابراهیمی کیست؟",
      "options": ["موسی", "ابراهیم", "نوح", "آدم"],
      "answer": "آدم"
    },
    {
      "id": 30,
      "question": "کشور کانادا در کدام قاره قرار دارد؟",
      "options": ["آسیا", "اروپا", "آمریکای شمالی", "اقیانوسیه"],
      "answer": "آمریکای شمالی"
    },
    {
      "id": 31,
      "question": "رود نیل در کدام قاره جاری است؟",
      "options": ["آسیا", "آفریقا", "اروپا", "آمریکا"],
      "answer": "آفریقا"
    },
    {
      "id": 32,
      "question": "کدام کشور بیشترین تولید نفت جهان را دارد؟",
      "options": ["آمریکا", "روسیه", "عربستان", "ایران"],
      "answer": "آمریکا"
    },
    {
      "id": 33,
      "question": "کدام حیوان نماد استرالیا است؟",
      "options": ["کانگورو", "شیر", "خرس پاندا", "کوالا"],
      "answer": "کانگورو"
    },
    {
      "id": 34,
      "question": "کدام دانشمند جاذبه را کشف کرد؟",
      "options": ["گالیله", "انیشتین", "نیوتن", "کپلر"],
      "answer": "نیوتن"
    },
    {
      "id": 35,
      "question": "رایانه به چه زبانی با یکدیگر ارتباط برقرار می‌کنند؟",
      "options": ["انگلیسی", "صفر و یک", "C++", "HTML"],
      "answer": "صفر و یک"
    },
    {
      "id": 36,
      "question": "پرچم کشور آلمان چه رنگ‌هایی دارد؟",
      "options": ["قرمز-سفید-آبی", "سبز-سفید-قرمز", "سیاه-قرمز-زرد", "آبی-زرد"],
      "answer": "سیاه-قرمز-زرد"
    },
    {
      "id": 37,
      "question": "بزرگترین جزیره جهان کدام است؟",
      "options": ["استرالیا", "گرینلند", "ماداگاسکار", "ایسلند"],
      "answer": "گرینلند"
    },
    {
      "id": 38,
      "question": "قاره استرالیا در نیمکره ... قرار دارد.",
      "options": ["شمالی", "جنوبی", "شرقی", "غربی"],
      "answer": "جنوبی"
    },
    {
      "id": 39,
      "question": "کدام کشور قدیمی‌ترین تمدن دنیا (بین‌النهرین) را داشته است؟",
      "options": ["ایران", "چین", "مصر", "عراق"],
      "answer": "عراق"
    },
    {
      "id": 40,
      "question": "قدیمی‌ترین دانشگاه جهان کدام است؟",
      "options": ["هاروارد", "آکسفورد", "القروین", "سوربن"],
      "answer": "القروین"
    },
    {
      "id": 41,
      "question": "کدام حیوان بیشترین طول عمر را دارد؟",
      "options": ["لاک‌پشت", "فیل", "نهنگ", "انسان"],
      "answer": "لاک‌پشت"
    },
    {
      "id": 42,
      "question": "کشور سوئیس به چه چیزی معروف است؟",
      "options": ["ساعت", "برج", "فرش", "چای"],
      "answer": "ساعت"
    },
    {
      "id": 43,
      "question": "پایتخت ترکیه کدام شهر است؟",
      "options": ["استانبول", "آنکارا", "ازمیر", "بورسا"],
      "answer": "آنکارا"
    },
    {
      "id": 44,
      "question": "کدام کشور به خاطر فوتبالش مشهور است؟",
      "options": ["برزیل", "آلمان", "آرژانتین", "ایتالیا"],
      "answer": "برزیل"
    },
    {
      "id": 45,
      "question": "پایتخت روسیه کدام شهر است؟",
      "options": ["سن‌پترزبورگ", "مسکو", "کی‌یف", "مینسک"],
      "answer": "مسکو"
    },
    {
      "id": 46,
      "question": "کدام کشور بیشترین جمعیت قاره اروپا را دارد؟",
      "options": ["فرانسه", "آلمان", "انگلستان", "روسیه"],
      "answer": "روسیه"
    },
    {
      "id": 47,
      "question": "مخترع لامپ الکتریکی چه کسی بود؟",
      "options": ["ادیسون", "انیشتین", "تسلا", "نیوتن"],
      "answer": "ادیسون"
    },
    {
      "id": 48,
      "question": "کدام سیاره حلقه‌های زیبایی دارد؟",
      "options": ["زحل", "مشتری", "اورانوس", "نپتون"],
      "answer": "زحل"
    },
    {
      "id": 49,
      "question": "طولانی‌ترین رود جهان کدام است؟",
      "options": ["نیل", "آمازون", "راین", "دجله"],
      "answer": "آمازون"
    },
    {
      "id": 50,
      "question": "کدام کشور به خاطر پیتزا معروف است؟",
      "options": ["فرانسه", "ایتالیا", "اسپانیا", "یونان"],
      "answer": "ایتالیا"
    }
  ]
}
